ISPTools/__init__.py
ISPTools/discovery/__init__.py
ISPTools/discovery/discover.py
ISPTools/main.py
ISPTools/Ping/__init__.py
ISPTools/Ping/hayping.py
ISPTools/Pool/__init__.py
ISPTools/Pool/pool.py
ISPTools/Ports/__init__.py
ISPTools/Ports/port.py
isptools-0.1.0.dist-info/entry_points.txt
isptools-0.1.0.dist-info/WHEEL
isptools-0.1.0.dist-info/METADATA
isptools-0.1.0.dist-info/RECORD
