Metadata-Version: 2.1
Name: isptools
Version: 0.1.0
Summary: Utilidades para un ISP
Keywords: ISP
Author: David Macanchi
Author-email: dmmacanchi@utpl.edu.ec
Requires-Python: >=3.8,<4.0
Classifier: Programming Language :: Python :: 3
Classifier: Programming Language :: Python :: 3.10
Classifier: Programming Language :: Python :: 3.8
Classifier: Programming Language :: Python :: 3.9
Requires-Dist: click (>=8.1.3,<9.0.0)
